LICENSE
README.md
gobomatic/__init__.py
gobomatic/blocks/__init__.py
gobomatic/blocks/control.py
gobomatic/blocks/events.py
gobomatic/blocks/looks.py
gobomatic/blocks/motion.py
gobomatic/blocks/operator.py
gobomatic/blocks/otherblocks.py
gobomatic/blocks/pen.py
gobomatic/blocks/sa.py
gobomatic/blocks/sensing.py
gobomatic/blocks/sound.py
gobomatic/primitives.py
gobomatic/project.py
gobomatic/py.typed
gobomatic-2.0.1.dist-info/LICENSE
gobomatic-2.0.1.dist-info/WHEEL
gobomatic-2.0.1.dist-info/METADATA
gobomatic-2.0.1.dist-info/RECORD
