Metadata-Version: 2.1
Name: gobomatic
Version: 2.0.1
Summary: Gobomatic is a Python library to generate Scratch (3>) projects from Object-Oriented representation of Scratch projects in Python code.
Home-page: https://github.com/aspizu/gobomatic
License: MIT
Author: aspizu
Author-email: aspizu@protonmail.com
Maintainer: aspizu
Maintainer-email: aspizu@protonmail.com
Classifier: License :: OSI Approved :: MIT License
Classifier: Programming Language :: Python :: 2
Classifier: Programming Language :: Python :: 2.7
Classifier: Programming Language :: Python :: 3
Classifier: Programming Language :: Python :: 3.10
Classifier: Programming Language :: Python :: 3.4
Classifier: Programming Language :: Python :: 3.5
Classifier: Programming Language :: Python :: 3.6
Classifier: Programming Language :: Python :: 3.7
Classifier: Programming Language :: Python :: 3.8
Classifier: Programming Language :: Python :: 3.9
Project-URL: Documentation, https://github.com/aspizu/gobomatic
Project-URL: Repository, https://github.com/aspizu/gobomatic
